solair/__about__.py
solair/__init__.py
solair-0.0.1a0.dev0.dist-info/METADATA
solair-0.0.1a0.dev0.dist-info/WHEEL
solair-0.0.1a0.dev0.dist-info/licenses/LICENSE.txt
solair-0.0.1a0.dev0.dist-info/RECORD
