Metadata-Version: 2.3
Name: solair
Version: 0.0.1a0.dev0
Summary: Analysis of solar modules from aerial infrared images of large solar power plants
Project-URL: Documentation, https://github.com/Sergiu Deitsch/solair#readme
Project-URL: Issues, https://github.com/Sergiu Deitsch/solair/issues
Project-URL: Source, https://github.com/Sergiu Deitsch/solair
Author-email: Sergiu Deitsch <sergiu.deitsch@gmail.com>
License: Apache-2.0
Classifier: Development Status :: 3 - Alpha
Classifier: Programming Language :: Python
Classifier: Programming Language :: Python :: 3.9
Classifier: Programming Language :: Python :: 3.10
Classifier: Programming Language :: Python :: 3.11
Classifier: Programming Language :: Python :: 3.12
Classifier: Programming Language :: Python :: 3.13
Classifier: Programming Language :: Python :: Implementation :: CPython
Classifier: Programming Language :: Python :: Implementation :: PyPy
Requires-Python: >=3.9
